python_systemd_dbus-0.0.3.dist-info/DESCRIPTION.rst
python_systemd_dbus-0.0.3.dist-info/METADATA
python_systemd_dbus-0.0.3.dist-info/RECORD
python_systemd_dbus-0.0.3.dist-info/WHEEL
python_systemd_dbus-0.0.3.dist-info/metadata.json
python_systemd_dbus-0.0.3.dist-info/pbr.json
python_systemd_dbus-0.0.3.dist-info/top_level.txt
systemd_dbus/__init__.py
systemd_dbus/automount.py
systemd_dbus/device.py
systemd_dbus/exceptions.py
systemd_dbus/job.py
systemd_dbus/manager.py
systemd_dbus/mount.py
systemd_dbus/path.py
systemd_dbus/property.py
systemd_dbus/service.py
systemd_dbus/snapshot.py
systemd_dbus/socket.py
systemd_dbus/swap.py
systemd_dbus/target.py
systemd_dbus/timer.py
systemd_dbus/unit.py
