Metadata-Version: 2.0
Name: python-systemd-dbus
Version: 0.0.3
Summary: Systemd interfaces wrapper
Home-page: UNKNOWN
Author: Wiliam Souza
Author-email: wiliam@mandriva.com
License: UNKNOWN
Platform: UNKNOWN
Classifier: Development Status :: 1 - Planning
Classifier: Intended Audience :: Developers
Classifier: License :: OSI Approved :: GNU General Public License v2 (GPLv2)
Classifier: Operating System :: POSIX :: Linux
Classifier: Programming Language :: Python
Classifier: Topic :: System :: Systems Administration
